Finwave_python_programs_setup/__init__.py
Finwave_python_programs_setup/file_utils.py
Finwave_python_programs_setup/root_utils.py
Finwave_python_programs_setup-0.0.2.dist-info/METADATA
Finwave_python_programs_setup-0.0.2.dist-info/WHEEL
Finwave_python_programs_setup-0.0.2.dist-info/top_level.txt
Finwave_python_programs_setup-0.0.2.dist-info/RECORD
