Metadata-Version: 2.1
Name: Finwave-python-programs-setup
Version: 0.0.2
Summary: Finwave Python Programs Setup
Home-page: UNKNOWN
Author: David May
Author-email: <david70may@gmail.com>
License: UNKNOWN
Keywords: python,Finwave
Platform: UNKNOWN
Classifier: Development Status :: 3 - Alpha
Classifier: Intended Audience :: Education
Classifier: Programming Language :: Python :: 2
Classifier: Programming Language :: Python :: 3
Classifier: Operating System :: MacOS :: MacOS X
Classifier: Operating System :: Microsoft :: Windows
